openai_model_router/__init__.py
openai_model_router-0.1.dist-info/LICENSE
openai_model_router-0.1.dist-info/METADATA
openai_model_router-0.1.dist-info/WHEEL
openai_model_router-0.1.dist-info/top_level.txt
openai_model_router-0.1.dist-info/RECORD
