Metadata-Version: 2.1
Name: openai-model-router
Version: 0.1
Summary: Automatically route your prompts to the best OpenAI model
Home-page: https://github.com/sambuddhabasu/openai_model_router
Author: Sambuddha Basu
License-File: LICENSE
Requires-Dist: openai (==0.27.8)
Requires-Dist: tiktoken (==0.4.0)
